wahlrecht/__init__.py
wahlrecht/__main__.py
wahlrecht/download.py
wahlrecht/parser.py
wahlrecht-0.0.2.dist-info/DESCRIPTION.rst
wahlrecht-0.0.2.dist-info/METADATA
wahlrecht-0.0.2.dist-info/RECORD
wahlrecht-0.0.2.dist-info/WHEEL
wahlrecht-0.0.2.dist-info/metadata.json
wahlrecht-0.0.2.dist-info/top_level.txt
